xy_git_api_tools/BaseModuleData.py
xy_git_api_tools/Git.py
xy_git_api_tools/Helper.py
xy_git_api_tools/ModuleData.py
xy_git_api_tools/Resource.py
xy_git_api_tools/Runner.py
xy_git_api_tools/__init__.py
xy_git_api_tools/execute/Main.py
xy_git_api_tools/execute/__init__.py
xy_git_api_tools/platform/GitConfig.py
xy_git_api_tools/platform/Platform.py
xy_git_api_tools/platform/Settings.py
xy_git_api_tools/platform/__init__.py
xy_git_api_tools/platform/gitcode/GitCode.py
xy_git_api_tools/platform/gitcode/__init__.py
xy_git_api_tools/platform/gitcode/urls.py
xy_git_api_tools/platform/gitee/Gitee.py
xy_git_api_tools/platform/gitee/__init__.py
xy_git_api_tools/platform/gitee/urls.py
xy_git_api_tools/platform/github/GitHub.py
xy_git_api_tools/platform/github/__init__.py
xy_git_api_tools/platform/github/urls.py
xy_git_api_tools/platform/gitlab/GitLab.py
xy_git_api_tools/platform/gitlab/__init__.py
xy_git_api_tools/platform/gitlab/urls.py
xy_git_api_tools-0.0.2.dist-info/LICENSE
xy_git_api_tools-0.0.2.dist-info/METADATA
xy_git_api_tools-0.0.2.dist-info/WHEEL
xy_git_api_tools-0.0.2.dist-info/entry_points.txt
xy_git_api_tools-0.0.2.dist-info/top_level.txt
xy_git_api_tools-0.0.2.dist-info/RECORD
