Metadata-Version: 2.1
Name: xy_git_api_tools
Version: 0.0.2
Summary: xy_git_api_tools 模块
Author-email: 余洋 <yuyangit.0515@qq.com>
Classifier: Programming Language :: Python :: 3
Requires-Python: >=3.11.3
License-File: LICENSE
Requires-Dist: importlib_resources
Requires-Dist: requests
Requires-Dist: xy_string
Requires-Dist: xy_console
Requires-Dist: xy_argparse
Requires-Dist: xy_settings
